main/__init__.py
main/main.py
mirrorbuddy-0.1.0.dist-info/METADATA
mirrorbuddy-0.1.0.dist-info/WHEEL
mirrorbuddy-0.1.0.dist-info/top_level.txt
mirrorbuddy-0.1.0.dist-info/RECORD
